custom_checkbox/__init__.py
custom_checkbox/example.py
custom_checkbox/frontend/build/asset-manifest.json
custom_checkbox/frontend/build/bootstrap.min.css
custom_checkbox/frontend/build/index.html
custom_checkbox/frontend/build/static/js/main.d02c9ca7.js
custom_checkbox/frontend/build/static/js/main.d02c9ca7.js.LICENSE.txt
custom_checkbox/frontend/build/static/js/main.d02c9ca7.js.map
streamlit_custom_checkbox-0.0.1.dist-info/LICENSE
streamlit_custom_checkbox-0.0.1.dist-info/METADATA
streamlit_custom_checkbox-0.0.1.dist-info/WHEEL
streamlit_custom_checkbox-0.0.1.dist-info/top_level.txt
streamlit_custom_checkbox-0.0.1.dist-info/RECORD
