Metadata-Version: 2.1
Name: streamlit-custom-checkbox
Version: 0.0.1
Summary: Streamlit component that allows you to do place checkboxes horizontally, and to have a default checkbox ('All')
Home-page: 
Author: yxneo
Author-email: john@example.com
Requires-Python: >=3.7
License-File: LICENSE
Requires-Dist: streamlit >=0.63
Provides-Extra: devel
Requires-Dist: wheel ; extra == 'devel'
Requires-Dist: pytest ==7.4.0 ; extra == 'devel'
Requires-Dist: playwright ==1.39.0 ; extra == 'devel'
Requires-Dist: requests ==2.31.0 ; extra == 'devel'
Requires-Dist: pytest-playwright-snapshot ==1.0 ; extra == 'devel'
Requires-Dist: pytest-rerunfailures ==12.0 ; extra == 'devel'
